{
    "songs": [
        {
            "song": "satin panties",
            "icon": "mom-icons",
            "color": "e66da4",
            "story": true
        },
        {
            "song": "high",
            "icon": "mom-icons",
            "color": "e66da4",
            "story": true
        },
        {
            "song": "m.i.l.f",
            "icon": "mom-icons",
            "color": "e66da4",
            "story": true
        }
    ],
    "hide_from_story_mode": false,
    "chars": [
        "mom",
        "bf",
        "gf"
    ],
    "week_name": "Mom",
    "difficulties": [
        "easy",
        "normal",
        "hard"
    ]
}